monolithe/__init__.py
monolithe/cli.py
monolithe/config.py
monolithe/courgette/__init__.py
monolithe/courgette/config.py
monolithe/courgette/courgette.py
monolithe/courgette/result.py
monolithe/courgette/lib/__init__.py
monolithe/courgette/lib/helper.py
monolithe/courgette/lib/maker.py
monolithe/courgette/lib/runner.py
monolithe/courgette/lib/sdkloader.py
monolithe/courgette/lib/testcase.py
monolithe/generators/__init__.py
monolithe/generators/sdkapiversiongenerator.py
monolithe/generators/sdkgenerator.py
monolithe/generators/lang/__init__.py
monolithe/generators/lang/csharp/__init__.py
monolithe/generators/lang/csharp/converter.py
monolithe/generators/lang/csharp/templates/AssemblyInfo.cs.tpl
monolithe/generators/lang/csharp/templates/fetcher.cs.tpl
monolithe/generators/lang/csharp/templates/model.cs.tpl
monolithe/generators/lang/csharp/templates/package.nuspec.tpl
monolithe/generators/lang/csharp/templates/sdkinfo.cs.tpl
monolithe/generators/lang/csharp/templates/session.cs.tpl
monolithe/generators/lang/csharp/templates/vspk.csproj.tpl
monolithe/generators/lang/csharp/templates/vspk.sln.tpl
monolithe/generators/lang/csharp/vanilla/LICENSE
monolithe/generators/lang/csharp/vanilla/README.md
monolithe/generators/lang/csharp/vanilla/__code_header
monolithe/generators/lang/csharp/vanilla/vspk/vspk/packages.config
monolithe/generators/lang/csharp/writers/__init__.py
monolithe/generators/lang/csharp/writers/apiversionwriter.py
monolithe/generators/lang/csharp/writers/vanillawriter.py
monolithe/generators/lang/go/__init__.py
monolithe/generators/lang/go/converter.py
monolithe/generators/lang/go/templates/model.go.tpl
monolithe/generators/lang/go/templates/sdkinfo.go.tpl
monolithe/generators/lang/go/templates/session.go.tpl
monolithe/generators/lang/go/vanilla/LICENSE
monolithe/generators/lang/go/vanilla/README.md
monolithe/generators/lang/go/vanilla/__code_header
monolithe/generators/lang/go/writers/__init__.py
monolithe/generators/lang/go/writers/apiversionwriter.py
monolithe-1.5.2.dist-info/LICENSE
monolithe-1.5.2.dist-info/METADATA
monolithe-1.5.2.dist-info/WHEEL
monolithe-1.5.2.dist-info/entry_points.txt
monolithe-1.5.2.dist-info/top_level.txt
monolithe-1.5.2.dist-info/RECORD
